.gitignore
.pre-commit-config.yaml
CITATION.cff
CONTRIBUTING.md
LICENCE
README.rst
pyproject.toml
setup.py
.github/workflows/comment-bot.yml
.github/workflows/test.yml
cuvec/CMakeLists.txt
cuvec/Config.cmake.in
cuvec/__init__.py
cuvec/_common.py
cuvec/_dist_ver.py
cuvec/pycuvec.py
cuvec/swigcuvec.py
cuvec.egg-info/PKG-INFO
cuvec.egg-info/SOURCES.txt
cuvec.egg-info/dependency_links.txt
cuvec.egg-info/requires.txt
cuvec.egg-info/top_level.txt
cuvec/include/cuvec.cuh
cuvec/include/cuvec.i
cuvec/include/pycuvec.cuh
cuvec/src/cuvec.cu
cuvec/src/swvec.i
cuvec/src/example_mod/CMakeLists.txt
cuvec/src/example_mod/example_mod.cu
cuvec/src/example_swig/CMakeLists.txt
cuvec/src/example_swig/example_swig.cu
cuvec/src/example_swig/example_swig.i
docs/index.md
docs/licence.md
docs/pydoc-markdown.yml
docs/requirements.txt
docs/custom_theme/css/extra.css
docs/custom_theme/js/extra.js
tests/__init__.py
tests/test_cuvec.py
tests/test_perf.py
tests/test_pycuvec.py
tests/test_swigcuvec.py