Metadata-Version: 2.1
Name: cuvec
Version: 2.12.0
Summary: Unifying Python/C++/CUDA memory: Python buffered array -> C++11 `std::vector` -> CUDA managed memory
Author-email: Casper da Costa-Luis <casper.dcl@physics.org>
License: MPL-2.0
Project-URL: documentation, https://amypad.github.io/CuVec
Project-URL: repository, https://github.com/AMYPAD/CuVec
Project-URL: changelog, https://github.com/AMYPAD/CuVec/releases
Keywords: Python,C,C++,buffer,vector,array,CUDA,CPython,SWIG,extensions,API
Classifier: Development Status :: 5 - Production/Stable
Classifier: Intended Audience :: Developers
Classifier: Environment :: GPU
Classifier: Environment :: GPU :: NVIDIA CUDA
Classifier: Intended Audience :: Education
Classifier: Intended Audience :: Science/Research
Classifier: License :: OSI Approved :: Mozilla Public License 2.0 (MPL 2.0)
Classifier: Operating System :: Microsoft :: Windows
Classifier: Operating System :: POSIX :: Linux
Classifier: Programming Language :: C
Classifier: Programming Language :: C++
Classifier: Programming Language :: Python :: 3
Classifier: Programming Language :: Python :: 3.7
Classifier: Programming Language :: Python :: 3.8
Classifier: Programming Language :: Python :: 3.9
Classifier: Programming Language :: Python :: 3.10
Classifier: Programming Language :: Python :: 3.11
Classifier: Programming Language :: Python :: 3 :: Only
Classifier: Topic :: Software Development :: Libraries
Classifier: Topic :: Software Development :: Libraries :: Python Modules
Classifier: Topic :: Utilities
Requires-Python: >=3.7
Provides-Extra: dev
License-File: LICENCE
